equationplot/__init__.py
equationplot/plotter.py
EquationPlot-0.1.1.dist-info/METADATA
EquationPlot-0.1.1.dist-info/WHEEL
EquationPlot-0.1.1.dist-info/top_level.txt
EquationPlot-0.1.1.dist-info/RECORD
