Metadata-Version: 2.1
Name: EquationPlot
Version: 0.1.1
Summary: A library to plot mathematical equations on a graph.
Home-page: https://medium.com/@diksha260303official/equationplot-a-python-library-for-effortless-graphing-of-mathematical-equations-c6270d2a15d1
Author: Diksha, Ayush Kumar Verma
Author-email: diksha260303official@gmail.com
Classifier: Programming Language :: Python :: 3
Classifier: License :: OSI Approved :: MIT License
Requires-Python: >=3.5
Requires-Dist: matplotlib
Requires-Dist: sympy
Requires-Dist: numpy
